datax/__init__.py
datax/runner.py
tests/__init__.py
tests/test_runner.py
datax-0.0.3.dist-info/LICENSE
datax-0.0.3.dist-info/METADATA
datax-0.0.3.dist-info/WHEEL
datax-0.0.3.dist-info/entry_points.txt
datax-0.0.3.dist-info/top_level.txt
datax-0.0.3.dist-info/RECORD
