Metadata-Version: 2.1
Name: datax
Version: 0.0.3
Summary: DataXplorer 
Home-page: https://github.com/Frechetta/DataXplorer
Author: Eric Frechette
Author-email: frechetta93@gmail.com
License: UNKNOWN
Keywords: data search query
Platform: UNKNOWN
Classifier: Programming Language :: Python
Requires-Python: >= 3.7
Requires-Dist: dxql (==0.0.6)
Requires-Dist: click (>=7.0)
Provides-Extra: test
Requires-Dist: pytest (>=5.0.1) ; extra == 'test'
Requires-Dist: pytest-cov (>=2.7.1) ; extra == 'test'
Requires-Dist: codecov (>=2.0.15) ; extra == 'test'
